CHANGES.rst
COPYING
MANIFEST.in
Makefile
README.rst
bootstrap-buildout.py
bootstrap-virtualenv.in
bootstrap-virtualenv.py
buildout.cfg
ez_setup.py
requirements-dev.in
requirements-dev.txt
requirements-test.in
requirements.in
requirements.txt
setup.cfg
setup.py
tox.ini
docs/Makefile
docs/api.rst
docs/changelogs.rst
docs/conf.py
docs/index.rst
docs/intro.rst
docs/make.bat
docs/locale/en/LC_MESSAGES/changelogs.po
docs/locale/en/LC_MESSAGES/cli.po
docs/locale/en/LC_MESSAGES/index.po
docs/locale/en/LC_MESSAGES/intro.po
docs/locale/ko/LC_MESSAGES/changelogs.po
docs/locale/ko/LC_MESSAGES/cli.po
docs/locale/ko/LC_MESSAGES/index.po
docs/locale/ko/LC_MESSAGES/intro.po
docs/locale/pot/changelogs.pot
docs/locale/pot/cli.pot
docs/locale/pot/index.pot
docs/locale/pot/intro.pot
docs/static/empty.css
mete0r.zipedit.egg-info/PKG-INFO
mete0r.zipedit.egg-info/SOURCES.txt
mete0r.zipedit.egg-info/dependency_links.txt
mete0r.zipedit.egg-info/not-zip-safe
mete0r.zipedit.egg-info/requires.txt
mete0r.zipedit.egg-info/top_level.txt
mete0r_zipedit/__init__.py
mete0r_zipedit/json_formatter.py
mete0r_zipedit/zipedit.py
mete0r_zipedit/locale/mete0r.zipedit.pot
mete0r_zipedit/locale/en/LC_MESSAGES/mete0r.zipedit.po
mete0r_zipedit/locale/ko/LC_MESSAGES/mete0r.zipedit.po
mete0r_zipedit/tests/__init__.py
mete0r_zipedit/tests/test_zipedit.py
mete0r_zipedit/tests/utils.py
mete0r_zipedit/tests/fixtures/__init__.py
mete0r_zipedit/tests/layers/__init__.py
virtualenv_support/README.rst