Metadata-Version: 1.1
Name: mete0r.zipedit
Version: 0.0.1
Summary: ZipFile editing
Home-page: UNKNOWN
Author: mete0r
Author-email: mete0r@sarangbang.or.kr
License: GNU Affero General Public License v3 or later (AGPLv3+)
Platform: UNKNOWN
Classifier: Development Status :: 1 - Planning
Classifier: License :: OSI Approved :: GNU Affero General Public License v3 or later (AGPLv3+)
